obelist/__init__.py
obelist/cli/__init__.py
obelist/cli/cmds/__init__.py
obelist/cli/cmds/debug.py
obelist/cli/cmds/format.py
obelist/cli/cmds/list.py
obelist/cli/cmds/parse.py
obelist/cli/cmds/path.py
obelist/core/__init__.py
obelist/core/app.py
obelist/core/config.py
obelist/core/format.py
obelist/core/handlers/__init__.py
obelist/core/handlers/jq.py
obelist/core/handlers/regex.py
obelist/core/handlers/xpath.py
obelist/core/parse.py
obelist/core/query.py
obelist/data/schemas/config.json
obelist/errors.py
obelist-0.0.0a2.dist-info/entry_points.txt
obelist-0.0.0a2.dist-info/LICENSE
obelist-0.0.0a2.dist-info/WHEEL
obelist-0.0.0a2.dist-info/METADATA
obelist-0.0.0a2.dist-info/RECORD
